{
    "Stars": [
        2,
        0,
        2,
        3,
        0,
        0,
        0,
        0,
        0,
        0,
        0,
        0,
        0,
        0,
        0,
        0,
        0,
        0,
        0,
        0,
        0,
        2,
        0,
        3,
        0,
        0,
        0,
        0,
        0,
        0
    ],
    "Trophy": 11,
    "Money": 749,
    "ActivitySkins": [
        true,
        false,
        true,
        false,
        false,
        false,
        false,
        false,
        false
    ],
    "NumberSelectedSkin": 3,
    "MusicActive": true,
    "SoundsActive": true,
    "Language": "ru",
    "intExample": 5,
    "strExample": "Hello!",
    "boolExample": [
        false,
        false,
        false,
        false
    ],
    "idSave": 46
}